mockssh/__init__.py
mockssh/conftest.py
mockssh/sample-user-key
mockssh/sample-user-key.pub
mockssh/server-key
mockssh/server-key.pub
mockssh/server.py
mockssh/sftp.py
mockssh/streaming.py
mockssh/test_server.py
mockssh/test_sftp.py
mockssh/test_streaming.py
mock_ssh_server-0.9.1.dist-info/LICENSE
mock_ssh_server-0.9.1.dist-info/METADATA
mock_ssh_server-0.9.1.dist-info/WHEEL
mock_ssh_server-0.9.1.dist-info/top_level.txt
mock_ssh_server-0.9.1.dist-info/RECORD
